preqtorch/__init__.py
preqtorch/encoders.py
preqtorch/replay.py
preqtorch/utils.py
preqtorch-0.1.5.dist-info/METADATA
preqtorch-0.1.5.dist-info/WHEEL
preqtorch-0.1.5.dist-info/licenses/LICENSE
preqtorch-0.1.5.dist-info/RECORD
