Metadata-Version: 2.4
Name: preqtorch
Version: 0.1.5
Summary: A package for prequential coding using PyTorch.
Project-URL: Homepage, https://github.com/cj-torres/preqtorch
Project-URL: Issues, https://github.com/cj-torres/preqtorch/issues
Author-email: Charles Torres <torrescj92@gmail.com>
License-File: LICENSE
Classifier: License :: OSI Approved :: MIT License
Classifier: Operating System :: OS Independent
Classifier: Programming Language :: Python :: 3
Requires-Python: >=3.11
Requires-Dist: numpy>=1.19.0
Requires-Dist: torch>=1.0.0
Requires-Dist: tqdm>=4.0.0
